<annotation>
	<folder>JPEGImages</folder>
	<filename>mask_withoutmask2199.jpg</filename>
	<path>C:\Users\Administrator\Desktop\VOCdevkit\VOC2007\JPEGImages\mask_withoutmask2199.jpg</path>
	<source>
		<database>Unknown</database>
	</source>
	<size>
		<width>1024</width>
		<height>722</height>
		<depth>3</depth>
	</size>
	<segmented>0</segmented>
	<object>
		<name>without-mask</name>
		<pose>Unspecified</pose>
		<truncated>0</truncated>
		<difficult>0</difficult>
		<bndbox>
			<xmin>256</xmin>
			<ymin>6</ymin>
			<xmax>481</xmax>
			<ymax>300</ymax>
		</bndbox>
	</object>
	<object>
		<name>without-mask</name>
		<pose>Unspecified</pose>
		<truncated>0</truncated>
		<difficult>0</difficult>
		<bndbox>
			<xmin>116</xmin>
			<ymin>45</ymin>
			<xmax>221</xmax>
			<ymax>162</ymax>
		</bndbox>
	</object>
</annotation>
