<annotation>
	<folder>JPEGImages</folder>
	<filename>mask_withoutmask6046.jpg</filename>
	<path>C:\Users\Administrator\Desktop\VOCdevkit\VOC2007\JPEGImages\mask_withoutmask6046.jpg</path>
	<source>
		<database>Unknown</database>
	</source>
	<size>
		<width>459</width>
		<height>336</height>
		<depth>3</depth>
	</size>
	<segmented>0</segmented>
	<object>
		<name>mask</name>
		<pose>Unspecified</pose>
		<truncated>0</truncated>
		<difficult>0</difficult>
		<bndbox>
			<xmin>182</xmin>
			<ymin>19</ymin>
			<xmax>353</xmax>
			<ymax>252</ymax>
		</bndbox>
	</object>
</annotation>
