<annotation>
	<folder>JPEGImages</folder>
	<filename>mask_withoutmask6008.jpg</filename>
	<path>C:\Users\Administrator\Desktop\VOCdevkit\VOC2007\JPEGImages\mask_withoutmask6008.jpg</path>
	<source>
		<database>Unknown</database>
	</source>
	<size>
		<width>580</width>
		<height>1256</height>
		<depth>3</depth>
	</size>
	<segmented>0</segmented>
	<object>
		<name>mask</name>
		<pose>Unspecified</pose>
		<truncated>0</truncated>
		<difficult>0</difficult>
		<bndbox>
			<xmin>172</xmin>
			<ymin>65</ymin>
			<xmax>324</xmax>
			<ymax>272</ymax>
		</bndbox>
	</object>
	<object>
		<name>mask</name>
		<pose>Unspecified</pose>
		<truncated>0</truncated>
		<difficult>0</difficult>
		<bndbox>
			<xmin>64</xmin>
			<ymin>529</ymin>
			<xmax>145</xmax>
			<ymax>627</ymax>
		</bndbox>
	</object>
	<object>
		<name>mask</name>
		<pose>Unspecified</pose>
		<truncated>0</truncated>
		<difficult>0</difficult>
		<bndbox>
			<xmin>229</xmin>
			<ymin>527</ymin>
			<xmax>343</xmax>
			<ymax>644</ymax>
		</bndbox>
	</object>
	<object>
		<name>mask</name>
		<pose>Unspecified</pose>
		<truncated>0</truncated>
		<difficult>0</difficult>
		<bndbox>
			<xmin>179</xmin>
			<ymin>829</ymin>
			<xmax>370</xmax>
			<ymax>1052</ymax>
		</bndbox>
	</object>
</annotation>
