<annotation>
	<folder>JPEGImages</folder>
	<filename>mask_withoutmask2953.jpg</filename>
	<path>C:\Users\Administrator\Desktop\VOCdevkit\VOC2007\JPEGImages\mask_withoutmask2953.jpg</path>
	<source>
		<database>Unknown</database>
	</source>
	<size>
		<width>760</width>
		<height>543</height>
		<depth>3</depth>
	</size>
	<segmented>0</segmented>
	<object>
		<name>mask</name>
		<pose>Unspecified</pose>
		<truncated>0</truncated>
		<difficult>0</difficult>
		<bndbox>
			<xmin>342</xmin>
			<ymin>67</ymin>
			<xmax>462</xmax>
			<ymax>199</ymax>
		</bndbox>
	</object>
</annotation>
