<annotation>
	<folder>JPEGImages</folder>
	<filename>mask_withoutmask2697.jpg</filename>
	<path>C:\Users\Administrator\Desktop\VOCdevkit\VOC2007\JPEGImages\mask_withoutmask2697.jpg</path>
	<source>
		<database>Unknown</database>
	</source>
	<size>
		<width>1024</width>
		<height>1540</height>
		<depth>3</depth>
	</size>
	<segmented>0</segmented>
	<object>
		<name>without-mask</name>
		<pose>Unspecified</pose>
		<truncated>0</truncated>
		<difficult>0</difficult>
		<bndbox>
			<xmin>405</xmin>
			<ymin>108</ymin>
			<xmax>530</xmax>
			<ymax>283</ymax>
		</bndbox>
	</object>
	<object>
		<name>without-mask</name>
		<pose>Unspecified</pose>
		<truncated>1</truncated>
		<difficult>0</difficult>
		<bndbox>
			<xmin>979</xmin>
			<ymin>133</ymin>
			<xmax>1024</xmax>
			<ymax>293</ymax>
		</bndbox>
	</object>
	<object>
		<name>without-mask</name>
		<pose>Unspecified</pose>
		<truncated>0</truncated>
		<difficult>0</difficult>
		<bndbox>
			<xmin>346</xmin>
			<ymin>204</ymin>
			<xmax>420</xmax>
			<ymax>303</ymax>
		</bndbox>
	</object>
	<object>
		<name>without-mask</name>
		<pose>Unspecified</pose>
		<truncated>0</truncated>
		<difficult>0</difficult>
		<bndbox>
			<xmin>200</xmin>
			<ymin>226</ymin>
			<xmax>301</xmax>
			<ymax>329</ymax>
		</bndbox>
	</object>
	<object>
		<name>without-mask</name>
		<pose>Unspecified</pose>
		<truncated>0</truncated>
		<difficult>0</difficult>
		<bndbox>
			<xmin>158</xmin>
			<ymin>175</ymin>
			<xmax>223</xmax>
			<ymax>270</ymax>
		</bndbox>
	</object>
</annotation>
